<cas:serviceResponse xmlns:cas='http://www.yale.edu/tp/cas'>
    <cas:authenticationSuccess>
        <cas:attributes>
            <cas:displayName>Rachel Roe</cas:displayName>
            <cas:uid>5551215</cas:uid>
            <cas:berkeleyEduIsMemberOf>cn=edu:berkeley:official:all-accounts-people-ou,ou=campus groups,dc=berkeley,dc=edu</cas:berkeleyEduIsMemberOf>
            <cas:berkeleyEduIsMemberOf>cn=edu:berkeley:org:libr:galc:galc-admins,ou=campus groups,dc=berkeley,dc=edu</cas:berkeleyEduIsMemberOf>
            <cas:berkeleyEduAffiliations>EMPLOYEE-TYPE-STAFF</cas:berkeleyEduAffiliations>
            <cas:berkeleyEduOfficialEmail>rroe@berkeley.test</cas:berkeleyEduOfficialEmail>
        </cas:attributes>
    </cas:authenticationSuccess>
</cas:serviceResponse>
